nepali_datetime_field/__init__.py
nepali_datetime_field/admin.py
nepali_datetime_field/apps.py
nepali_datetime_field/forms.py
nepali_datetime_field/models.py
nepali_datetime_field/tests.py
nepali_datetime_field/views.py
nepali_datetime_field/migrations/__init__.py
nepali_datetime_field/static/nepali_datetime_field/init.js
nepali_datetime_field/templates/nepali_datetime_field/forms/widgets/nepali_date.html
nepali_datetime_field/templatetags/__init__.py
nepali_datetime_field/templatetags/nepali_datetime_field.py
django_nepali_datetime_field-0.7.1.dist-info/LICENSE
django_nepali_datetime_field-0.7.1.dist-info/METADATA
django_nepali_datetime_field-0.7.1.dist-info/WHEEL
django_nepali_datetime_field-0.7.1.dist-info/top_level.txt
django_nepali_datetime_field-0.7.1.dist-info/RECORD
